semver_tools/__init__.py
semver_tools/git_utils.py
semver_tools/main.py
semver_tools/version_manager.py
tests/__init__.py
tests/test_git_utils.py
tests/test_main.py
tests/test_version_manager.py
semver_tools-0.1.0.dist-info/METADATA
semver_tools-0.1.0.dist-info/WHEEL
semver_tools-0.1.0.dist-info/entry_points.txt
semver_tools-0.1.0.dist-info/top_level.txt
semver_tools-0.1.0.dist-info/RECORD
