Metadata-Version: 2.4
Name: semver-tools
Version: 0.1.0
Summary: A tool for managing semantic versioning in Git repositories
Home-page: https://github.com/dpahima98/semver_tools
Author: Daniel Pahima
Author-email: dpahima98@gmail.com
Classifier: Programming Language :: Python :: 3
Classifier: License :: OSI Approved :: MIT License
Classifier: Operating System :: OS Independent
Requires-Python: >=3.6
Requires-Dist: GitPython
Requires-Dist: semantic-version
Dynamic: author
Dynamic: author-email
Dynamic: classifier
Dynamic: description
Dynamic: description-content-type
Dynamic: home-page
Dynamic: requires-dist
Dynamic: requires-python
Dynamic: summary
